{
	"name": "rawfolder",
	"properties": {
		"linkedServiceName": {
			"referenceName": "paramterlinkAzureDataLakeStorageS2",
			"type": "LinkedServiceReference"
		},
		"annotations": [],
		"type": "DelimitedText",
		"typeProperties": {
			"location": {
				"type": "AzureBlobFSLocation",
				"fileSystem": "filesoutput"
			},
			"columnDelimiter": ",",
			"escapeChar": "\\",
			"firstRowAsHeader": true,
			"quoteChar": "\""
		},
		"schema": [
			{
				"name": "Order Date",
				"type": "String"
			},
			{
				"name": "Customer First Name",
				"type": "String"
			},
			{
				"name": "Customer Last Name",
				"type": "String"
			},
			{
				"name": "Post Code",
				"type": "String"
			},
			{
				"name": "Region",
				"type": "String"
			},
			{
				"name": "Region Code",
				"type": "String"
			},
			{
				"name": "Product",
				"type": "String"
			},
			{
				"name": "Quantity",
				"type": "String"
			},
			{
				"name": "Sales$",
				"type": "String"
			}
		]
	},
	"type": "Microsoft.DataFactory/factories/datasets"
}